{
  "summary_ru": "Table, Diagram; A project whiteboard divided into columns (such as \"To Do\", \"In Progress\", and \"Done\") with handwritten notes, sticky notes, magnets, and a small printed sheet attached on the right. The board lists goals and task items …",
  "summary_en": "Table, Diagram; A project whiteboard divided into columns (such as \"To Do\", \"In Progress\", and \"Done\") with handwritten notes, sticky notes, magnets, and a small printed sheet attached on the right. The board lists goals and task items …",
  "bullets": [
    "Типы: Table, Diagram"
  ],
  "bullets_en": [
    "Types: Table, Diagram"
  ],
  "regions": 8,
  "source": "heuristic"
}