{
  "1": {
    "caption_en": "A teal three-column layout labeled \"01 WHY\", \"02 WHAT\", and \"03 HOW\". Each column poses a question: \"Why we updated the PIK?\", \"What is the new release all about?\", and \"How to get the new release?\".",
    "caption_ru": "A teal three-column layout labeled \"01 WHY\", \"02 WHAT\", and \"03 HOW\". Each column poses a question: \"Why we updated the PIK?\", \"What is the new release all about?\", and \"How to get the new release?\"."
  },
  "2": {
    "caption_en": "Close-up of a minimalist teal graphic showing a partial \"02\" in dark teal at the top-left, a diagonal dark line crossing the frame, and a partial white \"W\" at the bottom-right.\n\n{\n  \"type\": \"graphic\",\n  \"background_color\": \"teal\",\n  \"style\": \"minimalist / poster-like\",\n  \"elements\": [\n    {\n      \"element_type\": \"text\",\n      \"content\": \"02\",\n      \"color\": \"dark teal\",\n      \"position\": { \"x\": 0.12, \"y\": 0.10 },\n      \"size\": { \"width\": 0.40, \"height\": 0.36 },\n      \"alignment\": \"top-left\",\n      \"font_style\": \"bold, sans-serif\",\n      \"confidence\": 0.9\n    },\n    {\n      \"element_type\": \"line\",\n      \"color\": \"dark teal\",\n      \"start\": { \"x\": 0.05, \"y\": 0.75 },\n      \"end\": { \"x\": 0.95, \"y\": 0.20 },\n      \"thickness_relative\": 0.01,\n      \"orientation\": \"diagonal\",\n      \"confidence\": 0.92\n    },\n    {\n      \"element_type\": \"text\",\n      \"content\": \"W\",\n      \"color\": \"white\",\n      \"position\": { \"x\": 0.78, \"y\": 0.72 },\n      \"size\": { \"width\": 0.22, \"height\": 0.30 },\n      \"alignment\": \"bottom-right\",\n      \"font_style\": \"bold, sans-serif\",\n      \"confidence\": 0.88\n    }\n  ],\n  \"overall_confidence\": 0.9\n}",
    "caption_ru": "Close-up of a minimalist teal graphic showing a partial \"02\" in dark teal at the top-left, a diagonal dark line crossing the frame, and a partial white \"W\" at the bottom-right.\n\n{\n  \"type\": \"graphic\",\n  \"background_color\": \"teal\",\n  \"style\": \"minimalist / poster-like\",\n  \"elements\": [\n    {\n      \"element_type\": \"text\",\n      \"content\": \"02\",\n      \"color\": \"dark teal\",\n      \"position\": { \"x\": 0.12, \"y\": 0.10 },\n      \"size\": { \"width\": 0.40, \"height\": 0.36 },\n      \"alignment\": \"top-left\",\n      \"font_style\": \"bold, sans-serif\",\n      \"confidence\": 0.9\n    },\n    {\n      \"element_type\": \"line\",\n      \"color\": \"dark teal\",\n      \"start\": { \"x\": 0.05, \"y\": 0.75 },\n      \"end\": { \"x\": 0.95, \"y\": 0.20 },\n      \"thickness_relative\": 0.01,\n      \"orientation\": \"diagonal\",\n      \"confidence\": 0.92\n    },\n    {\n      \"element_type\": \"text\",\n      \"content\": \"W\",\n      \"color\": \"white\",\n      \"position\": { \"x\": 0.78, \"y\": 0.72 },\n      \"size\": { \"width\": 0.22, \"height\": 0.30 },\n      \"alignment\": \"bottom-right\",\n      \"font_style\": \"bold, sans-serif\",\n      \"confidence\": 0.88\n    }\n  ],\n  \"overall_confidence\": 0.9\n}"
  },
  "3": {
    "caption_en": "Three evenly spaced teal panels numbered 01–03 display headings \"WHY\", \"WHAT\", and \"HOW\" with short explanatory questions about a new release (e.g., \"Why we updated the PIK?\", \"What is the new release all about?\", \"How to get the new release?\").\n\n{\n  \"type\": \"three-column information panel\",\n  \"background_color\": \"teal/cyan\",\n  \"layout\": \"three equal columns, horizontally centered\",\n  \"language\": \"English\",\n  \"panels\": [\n    {\n      \"index\": 1,\n      \"number\": \"01\",\n      \"heading\": \"WHY\",\n      \"body_text\": \"Why we updated the PIK?\",\n      \"decorative_diagonal_line\": true,\n      \"text_colors\": {\n        \"number\": \"dark gray\",\n        \"heading\": \"white\",\n        \"body\": \"light gray/white\"\n      }\n    },\n    {\n      \"index\": 2,\n      \"number\": \"02\",\n      \"heading\": \"WHAT\",\n      \"body_text\": \"What is the new release all about?\",\n      \"decorative_diagonal_line\": true,\n      \"text_colors\": {\n        \"number\": \"dark gray\",\n        \"heading\": \"white\",\n        \"body\": \"light gray/white\"\n      }\n    },\n    {\n      \"index\": 3,\n      \"number\": \"03\",\n      \"heading\": \"HOW\",\n      \"body_text\": \"How to get the new release?\",\n      \"decorative_diagonal_line\": true,\n      \"text_colors\": {\n        \"number\": \"dark gray\",\n        \"heading\": \"white\",\n        \"body\": \"light gray/white\"\n      }\n    }\n  ],\n  \"ocr_text\": \"01 02 03 Why we updated the PIK? What is the new release all about? How to get the new release?\"\n}",
    "caption_ru": "Three evenly spaced teal panels numbered 01–03 display headings \"WHY\", \"WHAT\", and \"HOW\" with short explanatory questions about a new release (e.g., \"Why we updated the PIK?\", \"What is the new release all about?\", \"How to get the new release?\").\n\n{\n  \"type\": \"three-column information panel\",\n  \"background_color\": \"teal/cyan\",\n  \"layout\": \"three equal columns, horizontally centered\",\n  \"language\": \"English\",\n  \"panels\": [\n    {\n      \"index\": 1,\n      \"number\": \"01\",\n      \"heading\": \"WHY\",\n      \"body_text\": \"Why we updated the PIK?\",\n      \"decorative_diagonal_line\": true,\n      \"text_colors\": {\n        \"number\": \"dark gray\",\n        \"heading\": \"white\",\n        \"body\": \"light gray/white\"\n      }\n    },\n    {\n      \"index\": 2,\n      \"number\": \"02\",\n      \"heading\": \"WHAT\",\n      \"body_text\": \"What is the new release all about?\",\n      \"decorative_diagonal_line\": true,\n      \"text_colors\": {\n        \"number\": \"dark gray\",\n        \"heading\": \"white\",\n        \"body\": \"light gray/white\"\n      }\n    },\n    {\n      \"index\": 3,\n      \"number\": \"03\",\n      \"heading\": \"HOW\",\n      \"body_text\": \"How to get the new release?\",\n      \"decorative_diagonal_line\": true,\n      \"text_colors\": {\n        \"number\": \"dark gray\",\n        \"heading\": \"white\",\n        \"body\": \"light gray/white\"\n      }\n    }\n  ],\n  \"ocr_text\": \"01 02 03 Why we updated the PIK? What is the new release all about? How to get the new release?\"\n}"
  }
}