{
  "summary_ru": "Table; An ecosystem strategy canvas mapping platform components (services and devices) across journey stages — Home, Health, Work, Entertainment, Finance, Education, Mobility — and layered rows (Sustainability, Engagement, Inte…",
  "summary_en": "Table; An ecosystem strategy canvas mapping platform components (services and devices) across journey stages — Home, Health, Work, Entertainment, Finance, Education, Mobility — and layered rows (Sustainability, Engagement, Inte…",
  "bullets": [
    "Типы: Table"
  ],
  "bullets_en": [
    "Types: Table"
  ],
  "regions": 4,
  "source": "heuristic"
}