{
  "summary_ru": "Table; Platforms often exhibit a winner-takes-all dynamic: network effects make a platform more valuable as more consumers, producers, and partners join, enabling one ecosystem to grow faster, lower costs, and ultimately domina…",
  "summary_en": "Table; Platforms often exhibit a winner-takes-all dynamic: network effects make a platform more valuable as more consumers, producers, and partners join, enabling one ecosystem to grow faster, lower costs, and ultimately domina…",
  "bullets": [
    "Типы: Table"
  ],
  "bullets_en": [
    "Types: Table"
  ],
  "regions": 4,
  "source": "heuristic"
}